LICENSE
Makefile
README
sample
setup.py
test-trie-mod
this-pylint
trie_mod.py
trie_mod.egg-info/PKG-INFO
trie_mod.egg-info/SOURCES.txt
trie_mod.egg-info/dependency_links.txt
trie_mod.egg-info/top_level.txt