Metadata-Version: 1.1
Name: trie-mod
Version: 1.0
Summary: Pure Python trie nodule
Home-page: http://stromberg.dnsalias.org/~strombrg/trie-mod/
Author: Daniel Richard Stromberg
Author-email: strombrg@gmail.com
License: Apache v2
Keywords: Trie,dictionary-like,sorted dictionary
Platform: Cross platform
Classifier: Development Status :: 5 - Production/Stable
Classifier: Intended Audience :: Developers
Classifier: Programming Language :: Python :: 2
Classifier: Programming Language :: Python :: 3
